memoryawarestruct/__init__.py
memoryawarestruct/core/__init__.py
memoryawarestruct/core/memory.py
memoryawarestruct/utils/__init__.py
memoryawarestruct/utils/middleware.py
memoryawarestruct/utils/typedata.py
memoryawarestruct-0.0.13.dist-info/METADATA
memoryawarestruct-0.0.13.dist-info/WHEEL
memoryawarestruct-0.0.13.dist-info/top_level.txt
memoryawarestruct-0.0.13.dist-info/RECORD
