Metadata-Version: 2.2
Name: memoryawarestruct
Version: 0.0.13
Summary: MemoryAwareStruct is a secure and protected data structure system with high-level protection against unauthorized modification.
Home-page: https://github.com/LcfherShell/MemoryAwareStruct
Author: LcfherShell
Author-email: 
License: MIT
Classifier: Programming Language :: Python :: 3
Classifier: Operating System :: OS Independent
Requires-Python: >=3.6
Dynamic: author
Dynamic: classifier
Dynamic: description
Dynamic: description-content-type
Dynamic: home-page
Dynamic: license
Dynamic: requires-python
Dynamic: summary
